article_generator/__init__.py
article_generator/ai_client.py
article_generator/exceptions.py
article_generator/generator.py
article_generator/logging_config.py
article_generator/section.py
ai_article_generator-0.1.7.dist-info/METADATA
ai_article_generator-0.1.7.dist-info/WHEEL
ai_article_generator-0.1.7.dist-info/top_level.txt
ai_article_generator-0.1.7.dist-info/RECORD
