Metadata-Version: 2.4
Name: ai_article_generator
Version: 0.1.7
Summary: A Python library for generating articles using AI.
Author-email: Ihor Tykhonenko <tykhonenkoigor@gmail.com>
Requires-Python: >=3.8
Requires-Dist: openai>=1.0.0
Requires-Dist: httpx>=0.24.0
